login_auth_tui/__init__.py
login_auth_tui/__main__.py
login_auth_tui/aws_kion.py
login_auth_tui/aws_kion_check.py
login_auth_tui/aws_mfa.py
login_auth_tui/cli.py
login_auth_tui/dbx_token_rotate.py
login_auth_tui/kion_auth_password.py
login_auth_tui/kion_cli_password.py
login_auth_tui/noop.py
login_auth_tui/tui.py
login_auth_tui/tui.tcss
login_auth_tui/tui_bootstrap.py
login_auth_tui/util.py
login_auth_tui-0.4.dist-info/WHEEL
login_auth_tui-0.4.dist-info/entry_points.txt
login_auth_tui-0.4.dist-info/METADATA
login_auth_tui-0.4.dist-info/RECORD
