Metadata-Version: 2.4
Name: login-auth-tui
Version: 0.4
Summary: TUI for login-auth stuff
Author: Nicholas Hurley
License-Expression: CC0-1.0
Requires-Dist: click
Requires-Dist: textual>=6.4.0
Requires-Dist: pyyaml
Requires-Python: >=3.13, <3.14
Project-URL: CI, https://builds.sr.ht/~nwgh/login-auth-tui
Project-URL: Changelog, https://git.sr.ht/~nwgh/login-auth-tui/log
Project-URL: Homepage, https://sr.ht/~nwgh/login-auth-tui
Project-URL: Issues, https://todo.sr.ht/~nwgh/login-auth-tui
